HummingbirdLedButton.py
hummingbird_led_button/__init__.py
hummingbird_led_button/__main__.py
hummingbird_led_button/cli.py
hummingbird_led_button-0.0.5.dist-info/AUTHORS.rst
hummingbird_led_button-0.0.5.dist-info/LICENSE
hummingbird_led_button-0.0.5.dist-info/METADATA
hummingbird_led_button-0.0.5.dist-info/WHEEL
hummingbird_led_button-0.0.5.dist-info/entry_points.txt
hummingbird_led_button-0.0.5.dist-info/top_level.txt
hummingbird_led_button-0.0.5.dist-info/RECORD
